pyforge/__init__.py
pyforge/api.py
forge_client-0.1.0.dist-info/WHEEL
forge_client-0.1.0.dist-info/METADATA
forge_client-0.1.0.dist-info/RECORD
