Metadata-Version: 2.1
Name: forge-client
Version: 0.1.0
Summary: AutoDesk Forge API Python Client.
Home-page: https://github.com/yutayamazaki/pyforge
Author: yutayamazaki
Author-email: tppymd@gmail.com
Requires-Python: >=3.8,<4.0
Classifier: Programming Language :: Python :: 3
Classifier: Programming Language :: Python :: 3.8
Classifier: Programming Language :: Python :: 3.9
Requires-Dist: requests (>=2.25.1,<3.0.0)
Project-URL: Repository, https://github.com/yutayamazaki/pyforge
